evidentsource_functions/__init__.py
evidentsource_functions/content.py
evidentsource_functions/errors.py
evidentsource_functions/py.typed
evidentsource_functions/state_change.py
evidentsource_functions/state_view.py
evidentsource_functions/testing.py
evidentsource_functions/wit_types.py
evidentsource_functions/wasm/__init__.py
evidentsource_functions/wasm/adapters.py
evidentsource_functions/wasm/state_change/componentize_py_runtime.pyi
evidentsource_functions/wasm/state_change/componentize_py_types.py
evidentsource_functions/wasm/state_change/poll_loop.py
evidentsource_functions/wasm/state_change/componentize_py_async_support/__init__.py
evidentsource_functions/wasm/state_change/componentize_py_async_support/futures.py
evidentsource_functions/wasm/state_change/componentize_py_async_support/streams.py
evidentsource_functions/wasm/state_change/wit_world/__init__.py
evidentsource_functions/wasm/state_change/wit_world/imports/__init__.py
evidentsource_functions/wasm/state_change/wit_world/imports/cloudevents.py
evidentsource_functions/wasm/state_change/wit_world/imports/state_change_types.py
evidentsource_functions/wasm/state_change/wit_world/imports/state_view_types.py
evidentsource_functions/wasm/state_view/componentize_py_runtime.pyi
evidentsource_functions/wasm/state_view/componentize_py_types.py
evidentsource_functions/wasm/state_view/poll_loop.py
evidentsource_functions/wasm/state_view/componentize_py_async_support/__init__.py
evidentsource_functions/wasm/state_view/componentize_py_async_support/futures.py
evidentsource_functions/wasm/state_view/componentize_py_async_support/streams.py
evidentsource_functions/wasm/state_view/wit_world/__init__.py
evidentsource_functions/wasm/state_view/wit_world/imports/__init__.py
evidentsource_functions/wasm/state_view/wit_world/imports/cloudevents.py
evidentsource_functions/wasm/state_view/wit_world/imports/state_view_types.py
evidentsource_functions-1.0.0rc1.dist-info/METADATA
evidentsource_functions-1.0.0rc1.dist-info/WHEEL
evidentsource_functions-1.0.0rc1.dist-info/RECORD
