Metadata-Version: 2.4
Name: evidentsource-functions
Version: 1.0.0rc1
Summary: Python Server Functions library for building EvidentSource WASM state views and state changes
Author-email: Evident Systems <info@evidentsystems.com>
License-Expression: MIT OR Apache-2.0
Keywords: cqrs,event-driven,eventsourcing,wasi,wasm
Classifier: Development Status :: 3 - Alpha
Classifier: Intended Audience :: Developers
Classifier: License :: OSI Approved :: Apache Software License
Classifier: License :: OSI Approved :: MIT License
Classifier: Programming Language :: Python :: 3
Classifier: Programming Language :: Python :: 3.12
Classifier: Programming Language :: Python :: 3.13
Classifier: Typing :: Typed
Requires-Python: >=3.12
Requires-Dist: componentize-py>=0.17.0
Requires-Dist: evidentsource-core>=1.0.0-rc1
Provides-Extra: dev
Requires-Dist: mypy>=1.13.0; extra == 'dev'
Requires-Dist: pytest>=8.0.0; extra == 'dev'
Requires-Dist: ruff>=0.8.0; extra == 'dev'
